[
  {
    "id": "2025-0003",
    "title": "The Confessions",
    "creators": [
      "Augustine of Hippo"
    ],
    "year": 1900,
    "subjects": [
      "Patristics",
      "Autobiography"
    ],
    "collection": "Waypoint Classics",
    "language": "en",
    "type": "Book",
    "summary": "Augustine's meditation on faith, memory, and conversion in a modernized bilingual edition.",
    "tags": [
      "Non-Fiction",
      "Memoir",
      "Theology",
      "Biography"
    ],
    "quality": "A",
    "permalink": "record/2025-0003/",
    "normalized": {
      "title": "the confessions",
      "creators": [
        "augustine of hippo"
      ],
      "subjects": [
        "patristics",
        "autobiography"
      ],
      "collection": "waypoint classics"
    }
  },
  {
    "id": "2025-0004",
    "title": "Persuasion",
    "creators": [
      "Jane Austen"
    ],
    "year": 1891,
    "subjects": [
      "Fiction",
      "Romance"
    ],
    "collection": "Waypoint Classics",
    "language": "en",
    "type": "Novel",
    "summary": "Jane Austen's final completed novel in a reader-friendly critical edition.",
    "tags": [
      "Fiction",
      "Novel",
      "Romance"
    ],
    "quality": "A",
    "permalink": "record/2025-0004/",
    "normalized": {
      "title": "persuasion",
      "creators": [
        "jane austen"
      ],
      "subjects": [
        "fiction",
        "romance"
      ],
      "collection": "waypoint classics"
    }
  }
]
